{"stats":{"minecraft:custom":{"minecraft:time_since_rest":5753,"minecraft:play_one_minute":5753,"minecraft:crouch_one_cm":238,"minecraft:interact_with_furnace":2,"minecraft:walk_one_cm":16470,"minecraft:sneak_time":155,"minecraft:jump":11,"minecraft:leave_game":1,"minecraft:time_since_death":5753,"minecraft:fly_one_cm":15587},"minecraft:used":{"minecraft:furnace":1},"minecraft:crafted":{"minecraft:pink_dye":1},"minecraft:picked_up":{"beyondvanilla:lime_sweet_berries":3,"beyondvanilla:blue_sweet_berries":3,"beyondvanilla:orange_sweet_berries":3,"beyondvanilla:brown_sweet_berries":3,"beyondvanilla:magenta_sweet_berries":3,"minecraft:sweet_berries":2,"beyondvanilla:purple_sweet_berries":2,"beyondvanilla:white_sweet_berries":3,"beyondvanilla:light_gray_sweet_berries":4,"beyondvanilla:black_sweet_berries":2,"beyondvanilla:pink_sweet_berries":2,"beyondvanilla:yellow_sweet_berries":3,"beyondvanilla:green_sweet_berries":2,"beyondvanilla:light_blue_sweet_berries":2,"beyondvanilla:gray_sweet_berries":2,"beyondvanilla:cyan_sweet_berries":3}},"DataVersion":2567}